kagcolabserver.py
kagcolabserver-0.1.3.dist-info/LICENSE.txt
kagcolabserver-0.1.3.dist-info/METADATA
kagcolabserver-0.1.3.dist-info/WHEEL
kagcolabserver-0.1.3.dist-info/top_level.txt
kagcolabserver-0.1.3.dist-info/RECORD
