Metadata-Version: 2.1
Name: kagcolabserver
Version: 0.1.3
Summary: Automate the kaggle data import portion and run codeserver in that directory
Home-page: UNKNOWN
Author: Vijay Rahul
Author-email: vijayvenu1997@gmail.com
License: MIT
Platform: UNKNOWN
Requires-Dist: pyngrok (>=5.0.0)
Requires-Dist: kaggle
